toga_dummy/__init__.py
toga_dummy/app.py
toga_dummy/colors.py
toga_dummy/command.py
toga_dummy/dialogs.py
toga_dummy/factory.py
toga_dummy/fonts.py
toga_dummy/icons.py
toga_dummy/images.py
toga_dummy/paths.py
toga_dummy/screens.py
toga_dummy/statusicons.py
toga_dummy/utils.py
toga_dummy/window.py
toga_dummy/hardware/__init__.py
toga_dummy/hardware/camera.py
toga_dummy/hardware/location.py
toga_dummy/plugins/__init__.py
toga_dummy/plugins/image_formats.py
toga_dummy/resources/__init__.py
toga_dummy/resources/sample.png
toga_dummy/resources/screenshot.png
toga_dummy/resources/toga.png
toga_dummy/widgets/__init__.py
toga_dummy/widgets/activityindicator.py
toga_dummy/widgets/base.py
toga_dummy/widgets/box.py
toga_dummy/widgets/button.py
toga_dummy/widgets/canvas.py
toga_dummy/widgets/dateinput.py
toga_dummy/widgets/detailedlist.py
toga_dummy/widgets/divider.py
toga_dummy/widgets/imageview.py
toga_dummy/widgets/label.py
toga_dummy/widgets/mapview.py
toga_dummy/widgets/multilinetextinput.py
toga_dummy/widgets/numberinput.py
toga_dummy/widgets/optioncontainer.py
toga_dummy/widgets/passwordinput.py
toga_dummy/widgets/progressbar.py
toga_dummy/widgets/scrollcontainer.py
toga_dummy/widgets/selection.py
toga_dummy/widgets/slider.py
toga_dummy/widgets/splitcontainer.py
toga_dummy/widgets/switch.py
toga_dummy/widgets/table.py
toga_dummy/widgets/textinput.py
toga_dummy/widgets/timeinput.py
toga_dummy/widgets/tree.py
toga_dummy/widgets/webview.py
toga_dummy-0.5.2.dist-info/licenses/LICENSE
toga_dummy-0.5.2.dist-info/METADATA
toga_dummy-0.5.2.dist-info/WHEEL
toga_dummy-0.5.2.dist-info/entry_points.txt
toga_dummy-0.5.2.dist-info/top_level.txt
toga_dummy-0.5.2.dist-info/RECORD
